{
  "url": "https://muvees.sznm.dev/",
  "requestedUrl": "https://muvees.sznm.dev/",
  "timestamp": 1756685541072,
  "ranks": {
    "hundos": 5,
    "performance": 9,
    "accessibility": 9,
    "cumulative": 5
  },
  "lighthouse": {
    "version": "11.7.1",
    "performance": 0.87,
    "accessibility": 0.88,
    "bestPractices": 0.96,
    "seo": 1,
    "total": 371
  },
  "firstContentfulPaint": 2021.0274541830495,
  "firstMeaningfulPaint": 2021.0274541830495,
  "speedIndex": 2145.267136663978,
  "largestContentfulPaint": 3690.1112756510574,
  "totalBlockingTime": 131.86380572711892,
  "cumulativeLayoutShift": 0.0003392716740156119,
  "timeToInteractive": 4407.566182369484,
  "maxPotentialFirstInputDelay": 214,
  "timeToFirstByte": 82.118,
  "weight": {
    "summary": "71 requests • 1.4 MiB",
    "total": 1489229,
    "image": 1088681,
    "imageCount": 21,
    "script": 247690,
    "scriptCount": 20,
    "document": 21150,
    "font": 44212,
    "fontCount": 3,
    "stylesheet": 933,
    "stylesheetCount": 1,
    "thirdParty": 1095099,
    "thirdPartyCount": 3
  },
  "run": {
    "number": 1,
    "total": 1
  },
  "sidequests": {
    "-weight.total": 10,
    "+weight.total": 1,
    "-weight.document": 5,
    "+weight.document": 6,
    "-weight.script": 6,
    "+weight.script": 5,
    "-weight.image": 4,
    "+weight.image": 1,
    "-weight.font": 3,
    "+weight.font": 8,
    "+weight.fontCount": 3,
    "-timeToFirstByte": 5,
    "-totalBlockingTime": 5,
    "-largestContentfulPaint": 10
  },
  "axe": {
    "passes": 444,
    "violations": 41
  }
}