{
  "url": "https://xtarter.sznm.dev/",
  "requestedUrl": "https://xtarter.sznm.dev/",
  "timestamp": 1769386377887,
  "ranks": {
    "hundos": 3,
    "performance": 2,
    "accessibility": 5,
    "cumulative": 3
  },
  "lighthouse": {
    "version": "11.7.1",
    "performance": 0.98,
    "accessibility": 0.93,
    "bestPractices": 1,
    "seo": 1,
    "total": 391
  },
  "firstContentfulPaint": 907.4741999999999,
  "firstMeaningfulPaint": 923.4741999999999,
  "speedIndex": 1440.7275439461664,
  "largestContentfulPaint": 1867.9263999999998,
  "totalBlockingTime": 158,
  "cumulativeLayoutShift": 0.0001946555865560278,
  "timeToInteractive": 2990.7389999999996,
  "maxPotentialFirstInputDelay": 129,
  "timeToFirstByte": 3.6159999999999997,
  "weight": {
    "summary": "14 requests • 221.8 KiB",
    "total": 227119,
    "image": 0,
    "imageCount": 0,
    "script": 180025,
    "scriptCount": 9,
    "document": 13528,
    "font": 32303,
    "fontCount": 1,
    "stylesheet": 169,
    "stylesheetCount": 1,
    "thirdParty": 32303,
    "thirdPartyCount": 1
  },
  "run": {
    "number": 1,
    "total": 1
  },
  "sidequests": {
    "-weight.total": 2,
    "+weight.total": 7,
    "-weight.document": 3,
    "+weight.document": 6,
    "-weight.script": 2,
    "+weight.script": 7,
    "-weight.image": 1,
    "+weight.image": 4,
    "-weight.font": 2,
    "+weight.font": 7,
    "+weight.fontCount": 4,
    "-timeToFirstByte": 8,
    "-totalBlockingTime": 3,
    "-largestContentfulPaint": 2
  },
  "axe": {
    "passes": 222,
    "violations": 24
  }
}